urial/__init__.py
urial/__main__.py
urial-1.2.1.dist-info/LICENSE
urial-1.2.1.dist-info/METADATA
urial-1.2.1.dist-info/WHEEL
urial-1.2.1.dist-info/entry_points.txt
urial-1.2.1.dist-info/top_level.txt
urial-1.2.1.dist-info/RECORD
