Metadata-Version: 2.1
Name: urial
Version: 1.2.1
Summary: Add/update URIs in macOS Finder comments
Home-page: https://github.com/mhucka/urial
Author: Michael Hucka
Author-email: mhucka@caltech.edu
License: https://github.com/mhucka/urial/blob/main/LICENSE
Project-URL: Source Code, https://github.com/mhucka/urial
Project-URL: Bug Tracker, https://github.com/mhucka/urial/issues
Keywords: Python,utilities
Classifier: Development Status :: 3 - Alpha
Classifier: License :: OSI Approved :: BSD License
Classifier: Intended Audience :: Science/Research
Classifier: Operating System :: MacOS :: MacOS X
Classifier: Programming Language :: Python :: 3.8
Requires-Python: >=3.8
License-File: LICENSE
Requires-Dist: appscript ==1.2.2
Requires-Dist: plac ==1.4.2
Requires-Dist: sidetrack ==2.0.1
Requires-Dist: setuptools >=67.0.0
Requires-Dist: uritools ==4.0.2
